gradio_gradioworkbook/__init__.py
gradio_gradioworkbook/aiconfig_manager.py
gradio_gradioworkbook/events.py
gradio_gradioworkbook/gradio_workbook.py
gradio_gradioworkbook/gradio_workbook_component.py
gradio_gradioworkbook/gradio_workbook_component.pyi
gradio_gradioworkbook/gradioworkbook.pyi
gradio_gradioworkbook/session_data.py
gradio_gradioworkbook/utils.py
gradio_gradioworkbook/templates/component/__vite-browser-external-jWVCDlBL.js
gradio_gradioworkbook/templates/component/index.js
gradio_gradioworkbook/templates/component/style.css
gradio_gradioworkbook/templates/component/wrapper-6f348d45-pgNaiy2L.js
gradio_gradioworkbook/templates/example/index.js
gradio_gradioworkbook/templates/example/style.css
gradio_gradioworkbook-0.0.23.dist-info/METADATA
gradio_gradioworkbook-0.0.23.dist-info/WHEEL
gradio_gradioworkbook-0.0.23.dist-info/RECORD
