Metadata-Version: 2.1
Name: gradio_gradioworkbook
Version: 0.0.23
Summary: Workbook for interacting with models in AIConfig
Author: LastMile AI
License-Expression: MIT
Keywords: aiconfig,gradio-custom-component,gradio-template-Fallback,notebook,workbook
Requires-Python: >=3.8
Provides-Extra: dev
Requires-Dist: build; extra == 'dev'
Requires-Dist: twine; extra == 'dev'
